FastHTTPMock/__init__.py
FastHTTPMock/interaction.py
FastHTTPMock/keywords.py
FastHTTPMock/server.py
robotframework_fasthttpmock-0.1.1.dist-info/LICENSE
robotframework_fasthttpmock-0.1.1.dist-info/METADATA
robotframework_fasthttpmock-0.1.1.dist-info/WHEEL
robotframework_fasthttpmock-0.1.1.dist-info/entry_points.txt
robotframework_fasthttpmock-0.1.1.dist-info/top_level.txt
robotframework_fasthttpmock-0.1.1.dist-info/RECORD
