Metadata-Version: 2.2
Name: robotframework-fasthttpmock
Version: 0.1.1
Summary: HTTP mock server library for Robot Framework using FastAPI and Uvicorn
Author: Leela Prasad V
License: MIT License
Project-URL: Homepage, https://github.com/leelaprasadv/robotframework-fasthttpmock
Project-URL: Repository, https://github.com/leelaprasadv/robotframework-fasthttpmock.git
Keywords: robotframework,testing,mock,http
Requires-Python: >=3.8
License-File: LICENSE
Requires-Dist: robotframework>=7.0
Requires-Dist: fastapi>=0.110.0
Requires-Dist: uvicorn>=0.27.1
Requires-Dist: requests>=2.31.0
Requires-Dist: pydantic>=2.6.3
Provides-Extra: dev
Requires-Dist: pytest>=8.1.1; extra == "dev"
Requires-Dist: pytest-asyncio>=0.23.5; extra == "dev"
Requires-Dist: robotframework-requests==0.9.7; extra == "dev"
Requires-Dist: ruff>=0.9.2; extra == "dev"
Requires-Dist: black>=24.2.0; extra == "dev"
Requires-Dist: pytest-cov>=4.1.0; extra == "dev"
Requires-Dist: invoke>=2.2.0; extra == "dev"
Requires-Dist: build>=1.0.3; extra == "dev"
